[{"sicaklik":"27","nem":"75","sensor1":"54.00","sensor2":"700.00","sensor3":"342.00","sensor4":"47.00","sensor5":"167.00","sensor6":"141.00","sensor7":"142.00","tarih":"2018-11-07T12:22:48.986Z"},{"sicaklik":"28","nem":"75","sensor1":"57.00","sensor2":"703.00","sensor3":"342.00","sensor4":"50.00","sensor5":"164.00","sensor6":"145.00","sensor7":"142.00","tarih":"2018-11-07T12:22:50.845Z"},{"sicaklik":"28","nem":"75","sensor1":"56.00","sensor2":"705.00","sensor3":"344.00","sensor4":"49.00","sensor5":"165.00","sensor6":"147.00","sensor7":"143.00","tarih":"2018-11-07T12:22:52.708Z"},{"sicaklik":"28","nem":"75","sensor1":"54.00","sensor2":"702.00","sensor3":"344.00","sensor4":"49.00","sensor5":"164.00","sensor6":"142.00","sensor7":"141.00","tarih":"2018-11-07T12:22:54.565Z"},{"sicaklik":"28","nem":"75","sensor1":"53.00","sensor2":"703.00","sensor3":"343.00","sensor4":"46.00","sensor5":"166.00","sensor6":"145.00","sensor7":"142.00","tarih":"2018-11-07T12:22:56.424Z"},{"sicaklik":"28","nem":"75","sensor1":"54.00","sensor2":"703.00","sensor3":"345.00","sensor4":"49.00","sensor5":"162.00","sensor6":"144.00","sensor7":"140.00","tarih":"2018-11-07T12:22:58.284Z"},{"sicaklik":"28","nem":"75","sensor1":"55.00","sensor2":"700.00","sensor3":"344.00","sensor4":"46.00","sensor5":"165.00","sensor6":"144.00","sensor7":"142.00","tarih":"2018-11-07T12:23:00.143Z"},{"sicaklik":"28","nem":"75","sensor1":"57.00","sensor2":"701.00","sensor3":"341.00","sensor4":"48.00","sensor5":"165.00","sensor6":"144.00","sensor7":"143.00","tarih":"2018-11-07T12:23:02.003Z"},{"sicaklik":"28","nem":"75","sensor1":"56.00","sensor2":"701.00","sensor3":"342.00","sensor4":"50.00","sensor5":"163.00","sensor6":"146.00","sensor7":"142.00","tarih":"2018-11-07T12:23:03.863Z"},{"sicaklik":"28","nem":"75","sensor1":"51.00","sensor2":"703.00","sensor3":"339.00","sensor4":"50.00","sensor5":"164.00","sensor6":"145.00","sensor7":"142.00","tarih":"2018-11-07T12:23:05.723Z"},{"sicaklik":"28","nem":"75","sensor1":"53.00","sensor2":"703.00","sensor3":"342.00","sensor4":"48.00","sensor5":"162.00","sensor6":"144.00","sensor7":"141.00","tarih":"2018-11-07T12:23:07.582Z"},{"sicaklik":"28","nem":"75","sensor1":"52.00","sensor2":"702.00","sensor3":"339.00","sensor4":"46.00","sensor5":"162.00","sensor6":"146.00","sensor7":"138.00","tarih":"2018-11-07T12:23:09.442Z"},{"sicaklik":"28","nem":"75","sensor1":"53.00","sensor2":"703.00","sensor3":"340.00","sensor4":"49.00","sensor5":"163.00","sensor6":"145.00","sensor7":"145.00","tarih":"2018-11-07T12:23:11.302Z"},{"sicaklik":"28","nem":"75","sensor1":"56.00","sensor2":"702.00","sensor3":"341.00","sensor4":"49.00","sensor5":"164.00","sensor6":"144.00","sensor7":"141.00","tarih":"2018-11-07T12:23:13.162Z"},{"sicaklik":"28","nem":"75","sensor1":"54.00","sensor2":"699.00","sensor3":"341.00","sensor4":"51.00","sensor5":"164.00","sensor6":"147.00","sensor7":"139.00","tarih":"2018-11-07T12:23:15.022Z"},{"sicaklik":"28","nem":"75","sensor1":"54.00","sensor2":"702.00","sensor3":"342.00","sensor4":"49.00","sensor5":"164.00","sensor6":"144.00","sensor7":"141.00","tarih":"2018-11-07T12:23:16.881Z"},{"sicaklik":"28","nem":"75","sensor1":"57.00","sensor2":"700.00","sensor3":"339.00","sensor4":"48.00","sensor5":"163.00","sensor6":"146.00","sensor7":"139.00","tarih":"2018-11-07T12:23:18.740Z"},{"sicaklik":"28","nem":"75","sensor1":"56.00","sensor2":"696.00","sensor3":"340.00","sensor4":"47.00","sensor5":"163.00","sensor6":"144.00","sensor7":"141.00","tarih":"2018-11-07T12:23:20.599Z"},{"sicaklik":"28","nem":"75","sensor1":"56.00","sensor2":"697.00","sensor3":"342.00","sensor4":"49.00","sensor5":"164.00","sensor6":"145.00","sensor7":"143.00","tarih":"2018-11-07T12:23:22.460Z"},{"sicaklik":"28","nem":"75","sensor1":"61.00","sensor2":"699.00","sensor3":"337.00","sensor4":"48.00","sensor5":"165.00","sensor6":"144.00","sensor7":"139.00","tarih":"2018-11-07T12:23:24.320Z"},{"sicaklik":"28","nem":"75","sensor1":"55.00","sensor2":"697.00","sensor3":"338.00","sensor4":"49.00","sensor5":"161.00","sensor6":"142.00","sensor7":"139.00","tarih":"2018-11-07T12:23:26.178Z"},{"sicaklik":"28","nem":"76","sensor1":"59.00","sensor2":"697.00","sensor3":"346.00","sensor4":"50.00","sensor5":"160.00","sensor6":"141.00","sensor7":"143.00","tarih":"2018-11-07T12:23:28.039Z"},{"sicaklik":"28","nem":"76","sensor1":"55.00","sensor2":"696.00","sensor3":"341.00","sensor4":"50.00","sensor5":"162.00","sensor6":"142.00","sensor7":"141.00","tarih":"2018-11-07T12:23:29.898Z"},{"sicaklik":"28","nem":"76","sensor1":"58.00","sensor2":"699.00","sensor3":"340.00","sensor4":"50.00","sensor5":"163.00","sensor6":"145.00","sensor7":"138.00","tarih":"2018-11-07T12:23:31.758Z"},{"sicaklik":"28","nem":"76","sensor1":"56.00","sensor2":"698.00","sensor3":"339.00","sensor4":"50.00","sensor5":"164.00","sensor6":"145.00","sensor7":"139.00","tarih":"2018-11-07T12:23:33.617Z"},{"sicaklik":"28","nem":"76","sensor1":"57.00","sensor2":"699.00","sensor3":"338.00","sensor4":"48.00","sensor5":"162.00","sensor6":"144.00","sensor7":"141.00","tarih":"2018-11-07T12:23:35.478Z"},{"sicaklik":"28","nem":"76","sensor1":"54.00","sensor2":"699.00","sensor3":"339.00","sensor4":"48.00","sensor5":"162.00","sensor6":"145.00","sensor7":"140.00","tarih":"2018-11-07T12:23:37.337Z"},{"sicaklik":"28","nem":"76","sensor1":"57.00","sensor2":"696.00","sensor3":"341.00","sensor4":"52.00","sensor5":"159.00","sensor6":"142.00","sensor7":"140.00","tarih":"2018-11-07T12:23:39.197Z"},{"sicaklik":"28","nem":"76","sensor1":"57.00","sensor2":"698.00","sensor3":"338.00","sensor4":"51.00","sensor5":"160.00","sensor6":"146.00","sensor7":"140.00","tarih":"2018-11-07T12:23:41.057Z"},{"sicaklik":"28","nem":"76","sensor1":"61.00","sensor2":"693.00","sensor3":"343.00","sensor4":"48.00","sensor5":"160.00","sensor6":"147.00","sensor7":"137.00","tarih":"2018-11-07T12:23:42.916Z"},{"sicaklik":"28","nem":"76","sensor1":"58.00","sensor2":"697.00","sensor3":"339.00","sensor4":"50.00","sensor5":"163.00","sensor6":"147.00","sensor7":"142.00","tarih":"2018-11-07T12:23:44.776Z"},{"sensor1Alan":3105648,"sensor2Alan":39042770,"sensor3Alan":19025319.5,"sensor4Alan":2725345,"sensor5Alan":9093767,"sensor6Alan":8059801,"sensor7Alan":7855.240999999999,"koklamaSinifi":"A"}]